pytest_timer/__init__.py
pytest_timer/plugin.py
pytest_timer-1.0.0.dist-info/LICENSE
pytest_timer-1.0.0.dist-info/METADATA
pytest_timer-1.0.0.dist-info/WHEEL
pytest_timer-1.0.0.dist-info/entry_points.txt
pytest_timer-1.0.0.dist-info/top_level.txt
pytest_timer-1.0.0.dist-info/RECORD
