Metadata-Version: 2.1
Name: pytest-timer
Version: 1.0.0
Summary: A timer plugin for pytest
Home-page: https://github.com/skudriashev/pytest-timer
Author: Stanislav Kudriashev
License: MIT
Classifier: Intended Audience :: Developers
Classifier: License :: OSI Approved :: MIT License
Classifier: Natural Language :: English
Classifier: Operating System :: OS Independent
Classifier: Programming Language :: Python
Classifier: Programming Language :: Python :: 3
Classifier: Programming Language :: Python :: 3.8
Classifier: Programming Language :: Python :: 3.9
Classifier: Programming Language :: Python :: 3.10
Classifier: Programming Language :: Python :: 3.11
Classifier: Programming Language :: Python :: 3.12
Classifier: Programming Language :: Python :: Implementation :: CPython
Classifier: Topic :: Software Development :: Testing
Classifier: Environment :: Console
Classifier: Framework :: Pytest
License-File: LICENSE
Requires-Dist: pytest
Provides-Extra: colorama
Requires-Dist: colorama ; extra == 'colorama'
Provides-Extra: termcolor
Requires-Dist: termcolor ; extra == 'termcolor'
